RandomNameGen/Error_Handling.py
RandomNameGen/Prefix.py
RandomNameGen/RandomName.py
RandomNameGen/Suffix.py
RandomNameGen/__init__.py
RandomNameGenerator_RememberThisUser-0.0.3.dist-info/METADATA
RandomNameGenerator_RememberThisUser-0.0.3.dist-info/WHEEL
RandomNameGenerator_RememberThisUser-0.0.3.dist-info/entry_points.txt
RandomNameGenerator_RememberThisUser-0.0.3.dist-info/top_level.txt
RandomNameGenerator_RememberThisUser-0.0.3.dist-info/RECORD
