Metadata-Version: 2.1
Name: RandomNameGenerator-RememberThisUser
Version: 0.0.3
Summary: Creates a random name that you can customize with functions.
Author: RememberThisUser
Author-email: tatelkirkmatthew@gmail.com
Classifier: Development Status :: 3 - Alpha
Classifier: Intended Audience :: Developers
Classifier: License :: OSI Approved :: MIT License
Classifier: Programming Language :: Python :: 3.10
Classifier: Programming Language :: Python :: 3.11
Requires-Dist: random
Requires-Dist: inspect
